README.md
setup.cfg
setup.py
lcc/__init__.py
lcc.egg-info/PKG-INFO
lcc.egg-info/SOURCES.txt
lcc.egg-info/dependency_links.txt
lcc.egg-info/entry_points.txt
lcc.egg-info/requires.txt
lcc.egg-info/top_level.txt
lcc/bin/__init__.py
lcc/bin/create_project.py
lcc/bin/filter_stars.py
lcc/bin/make_filter.py
lcc/bin/plot_lcs.py
lcc/bin/prepare_query.py
lcc/cli/__init__.py
lcc/cli/input_parse.py
lcc/cli/lcc.py
lcc/cli/stars_handling.py
lcc/data_manager/__init__.py
lcc/data_manager/filter_serializer.py
lcc/data_manager/package_reader.py
lcc/data_manager/prepare_package.py
lcc/data_manager/status_resolver.py
lcc/db_tier/TAP_query.py
lcc/db_tier/__init__.py
lcc/db_tier/base_query.py
lcc/db_tier/stars_provider.py
lcc/db_tier/vizier_tap_base.py
lcc/db_tier/connectors/__init__.py
lcc/db_tier/connectors/asas.py
lcc/db_tier/connectors/catalina.py
lcc/db_tier/connectors/corot.py
lcc/db_tier/connectors/file_manager.py
lcc/db_tier/connectors/kepler.py
lcc/db_tier/connectors/macho.py
lcc/db_tier/connectors/ogleII.py
lcc/db_tier/connectors/ogleIII.py
lcc/entities/__init__.py
lcc/entities/exceptions.py
lcc/entities/light_curve.py
lcc/entities/star.py
lcc/stars_processing/__init__.py
lcc/stars_processing/stars_filter.py
lcc/stars_processing/deciders/__init__.py
lcc/stars_processing/deciders/custom_decider.py
lcc/stars_processing/deciders/neuron_decider.py
lcc/stars_processing/deciders/supervised_deciders.py
lcc/stars_processing/deciders/unsupervised/__init__.py
lcc/stars_processing/deciders/unsupervised/k_means_decider.py
lcc/stars_processing/descriptors/__init__.py
lcc/stars_processing/descriptors/abbe_value_descr.py
lcc/stars_processing/descriptors/color_index_descr.py
lcc/stars_processing/descriptors/curve_density_descr.py
lcc/stars_processing/descriptors/curve_descr.py
lcc/stars_processing/descriptors/curves_shape_descr.py
lcc/stars_processing/descriptors/hist_shape_descr.py
lcc/stars_processing/descriptors/kurtosis_desc.py
lcc/stars_processing/descriptors/position_descriptor.py
lcc/stars_processing/descriptors/property_desc.py
lcc/stars_processing/descriptors/skewness_desc.py
lcc/stars_processing/descriptors/variogram_shape_descr.py
