Metadata-Version: 1.1
Name: lcc
Version: 1.2.3
Summary: Light Curves Classifier is package for classification stars by using their light curves and metadata
Home-page: https://github.com/mavrix93/LightCurvesClassifier
Author: Martin Vo
Author-email: mavrix@seznam.cz
License: UNKNOWN
Download-URL: https://github.com/mavrix93/LightCurvesClassifier/archive/v1.0.0.tar.gz
Keywords: light curves,machine-learning,astronomy,data-mining
Platform: UNKNOWN
Classifier: Development Status :: 4 - Beta
Classifier: Programming Language :: Python :: 3
Classifier: Programming Language :: Python :: 3.6
